pyedurov3/__init__.py
pyedurov3/__main__.py
pyedurov3/errors.py
pyedurov3/utility.py
pyedurov3/hardware/__init__.py
pyedurov3/hardware/arduino.py
pyedurov3/hardware/button.py
pyedurov3/hardware/camera.py
pyedurov3/hardware/display.py
pyedurov3/hardware/led.py
pyedurov3/hardware/system.py
pyedurov3/hardware/mock/__init__.py
pyedurov3/hardware/mock/arduino.py
pyedurov3/hardware/mock/camera.py
pyedurov3/hardware/mock/system.py
pyedurov3/images/batteryError.png
pyedurov3/images/cameraError.png
pyedurov3/images/clientError.png
pyedurov3/images/error.png
pyedurov3/images/microcontrollerError.png
pyedurov3/images/networkError.png
pyedurov3/server/__init__.py
pyedurov3/server/advertising.py
pyedurov3/server/cameraserver.py
pyedurov3/server/ioserver.py
pyedurov3/server/localui.py
pyedurov3/server/webserver.py
pyedurov3/system/__init__.py
pyedurov3/system/pyedurov3.service
pyedurov3/web/favicon.ico
pyedurov3/web/index.html
pyedurov3/web/scripts/globalData.js
pyedurov3/web/scripts/index.js
pyedurov3/web/scripts/input.js
pyedurov3/web/scripts/ioclient.js
pyedurov3/web/scripts/joy.js
pyedurov3/web/scripts/pageManager.js
pyedurov3/web/scripts/settings.js
pyedurov3/web/scripts/video.js
pyedurov3/web/static/.gitignore
pyedurov3/web/static/bootstrap-icons.css
pyedurov3/web/static/bootstrap.css
pyedurov3/web/static/style.css
pyedurov3-0.0.2.dist-info/LICENSE
pyedurov3-0.0.2.dist-info/METADATA
pyedurov3-0.0.2.dist-info/WHEEL
pyedurov3-0.0.2.dist-info/top_level.txt
pyedurov3-0.0.2.dist-info/RECORD
