Metadata-Version: 2.1
Name: pyedurov3
Version: 0.0.2
Summary: Server package for Edu-ROV hardware V4.0
Author-email: Simen Tinderholt <simtind@gmail.com>, Jan Kettler <placeholder@gmail.com>
Project-URL: Homepage, https://github.com/simtind/edu-rover2-server
Project-URL: Bug Tracker, https://github.com/simtind/edu-rover2-server/issues
Classifier: Development Status :: 3 - Alpha
Classifier: License :: OSI Approved :: GNU General Public License v3 (GPLv3)
Classifier: Programming Language :: Python :: 3.7
Requires-Python: >=3.7
License-File: LICENSE
Requires-Dist: picamera
Requires-Dist: sense-hat
Requires-Dist: pyserial-asyncio
Requires-Dist: asyncio
Requires-Dist: psutil
Requires-Dist: websockets
Requires-Dist: aiortc
Requires-Dist: aiohttp
Requires-Dist: adafruit-circuitpython-ssd1306
